[
  {
    "id": "1772010943833-vjlwcc7hh",
    "user_id": "guest-user",
    "title": "火种守护者",
    "story": "故事内容\n故事内容\n### 核心概念\n在擎天柱和威震天的战争之前，一群古老的变形金刚守护者为了保护火种源，与邪恶的宇宙大帝展开了一场跨越星系的战争。\n\n### 故事梗概\n在遥远的过去，当塞伯坦还是一个和平的星球时，火种源的守护者们负责保护这个赋予变形金刚生命的神秘能量体。其中，最年轻的守护者奥米加渴望证明自己的价值，却在一次任务中意外释放了被封印的宇宙大帝碎片。\n\n宇宙大帝的碎片迅速感染了部分变形金刚，将它们变成了邪恶的破坏者。为了阻止宇宙大帝的复活，奥米加和其他守护者踏上了寻找碎片的旅程。在旅途中，他们遇到了来自不同星球的变形金刚盟友，也遭遇了宇宙大帝的忠实追随者。\n\n奥米加逐渐发现，宇宙大帝的复活并非偶然，而是塞伯坦内部的阴谋。一些变形金刚为了获得更强大的力量，故意释放了宇宙大帝的碎片。在最终的决战中，奥米加必须在拯救塞伯坦和保护火种源之间做出选择。\n\n最终，奥米加牺牲了自己，将宇宙大帝的碎片重新封印，但他的精神永远融入了火种源，成为了所有变形金刚的精神象征。多年后，当擎天柱和威震天的战争爆发时，奥米加的力量依然在守护着塞伯坦。\n\n### 番外特色\n- 探索变形金刚的起源故事\n- 引入新的变形金刚角色和种族\n- 展示塞伯坦的古老文明\n- 揭示火种源的秘密\n- 为变形金刚宇宙增添深度和广度",
    "style": "realistic",
    "shot_count": 9,
    "stage": "scenes",
    "created_at": "2026-02-25T09:15:43.833Z",
    "updated_at": "2026-02-25T09:17:24.560Z"
  },
  {
    "id": "1772014099025-nrloe4j3q",
    "user_id": "guest-user",
    "title": "《寂静归档》",
    "story": "核心设定：在一个所有纸质书籍已被禁止、记忆可被数字化“清理”的近未来社会，一名图书管理员在废弃的国家档案馆深处，发现了一本无法被扫描、也无法被销毁的皮质古书。每当有人阅读它，书中就会浮现出阅读者内心最深处的恐惧，并逐渐在现实中实体化。\n恐怖点：恐惧的“定制化”。怪物并非固定形态，而是每个人内心创伤的投射。档案馆本身就像一个不断变化的迷宫，由读者的集体潜意识构筑。\n视觉提示：无尽的高耸书架、蠕动的文字从书页中爬出、阴影凝聚成个人化的恐怖形象、复古的皮质书封与现代极简的档案馆形成强烈对比。",
    "style": "realistic",
    "shot_count": 9,
    "stage": "images",
    "created_at": "2026-02-25T10:08:19.025Z",
    "updated_at": "2026-02-26T04:36:37.001Z"
  }
]